LICENSE
MANIFEST.in
README.rst
distribute_setup.py
setup.py
winreg_unicode.py
winreg_unicode.egg-info/PKG-INFO
winreg_unicode.egg-info/SOURCES.txt
winreg_unicode.egg-info/dependency_links.txt
winreg_unicode.egg-info/top_level.txt
winreg_unicode.egg-info/zip-safe