Metadata-Version: 1.1
Name: winreg-unicode
Version: 0.5.0
Summary: a Unicode-aware winreg package for Python 2
Home-page: http://stutzbachenterprises.com/
Author: Stutzbach Enterprises, LLC
Author-email: daniel@stutzbachenterprises.com
License: BSD
Keywords: winreg unicode Windows registry
Platform: UNKNOWN
Classifier: Development Status :: 4 - Beta
Classifier: Environment :: Win32 (MS Windows)
Classifier: Operating System :: Microsoft :: Windows
Classifier: Intended Audience :: Developers
Classifier: License :: OSI Approved :: BSD License
Classifier: Topic :: Software Development :: Libraries :: Python Modules
Classifier: Programming Language :: Python :: 2
Classifier: Programming Language :: Python :: 2.5
Classifier: Programming Language :: Python :: 2.6
Classifier: Programming Language :: Python :: 2.7
Provides: winreg_unicode
